{
    "production": false,
    "app": {
        "host": "0.0.0.0",
        "port": 3001,
        "cors": {
            "credentials": true,
            "origin": true
        }
    },
    "database": {
        "host": "movie_rating_db",
        "port": 5432,
        "username": "root",
        "password": "root",
        "database": "postgres",
        "logging": "false",
        "ssl": false
    },
    "event_store": {
        "host": "event_store_db",
        "port": 5432,
        "username": "root",
        "password": "root",
        "database": "postgres",
        "logging": "false",
        "ssl": false
    },
    "message_broker": {
        "host": "kafka",
        "port": 9092
    },
    "jwt": {
        "secret": "secret",
        "expiration": 28800
    }
}
